{"id": "click.termui", "path": "/Users/buckleyd/Projects/pulse/.env/lib/mypy/typeshed/third_party/2and3/click/termui.pyi", "mtime": 1524071782, "size": 3309, "hash": "f8005e1f16b5d2283c48ddf57140c45c", "data_mtime": 1525469037, "dependencies": ["typing", "click.types", "click._termui_impl", "builtins"], "suppressed": [], "child_modules": [], "options": {"warn_return_any": false, "strict_optional_whitelist": null, "follow_imports_for_stubs": false, "disallow_untyped_calls": false, "platform": "darwin", "disallow_any_explicit": false, "cache_fine_grained": false, "always_true": [], "ignore_missing_imports": true, "check_untyped_defs": false, "strict_boolean": false, "disallow_any_expr": false, "disallow_untyped_defs": false, "quick_and_dirty": false, "disallow_any_decorated": false, "warn_unused_ignores": true, "ignore_errors": false, "warn_no_return": true, "no_implicit_optional": false, "always_false": [], "strict_optional": true, "disallow_untyped_decorators": false, "follow_imports": "normal", "disallow_subclassing_any": false, "show_none_errors": true, "disallow_any_generics": false, "disallow_any_unimported": false}, "dep_prios": [5, 5, 5, 5], "dep_lines": [1, 14, 15, 1], "interface_hash": "5580d52a27506a8944b7f75af6a3950f", "version_id": "0.590", "ignore_all": false}
